ambient_wx/__init__.py
ambient_wx/_version.py
ambient_wx/ambient_wx.py
ambient_wx/api.py
ambient_wx/tests/__init__.py
ambient_wx/tests/test_ambient_wx.py
ambient_wx/tests/test_api.py
ambient_wx-0.1.3.dist-info/METADATA
ambient_wx-0.1.3.dist-info/WHEEL
ambient_wx-0.1.3.dist-info/RECORD
