Metadata-Version: 2.1
Name: ambient-wx
Version: 0.1.3
Summary: API Wrapper for the Ambient Weather Station API with meteorological units and pandas functionality as well
License: MIT
Keywords: weather,ambient weather
Author: Barry Martin
Author-email: barry.martin@thepythongeek.com
Requires-Python: >=3.9,<4.0
Classifier: License :: OSI Approved :: MIT License
Classifier: Programming Language :: Python
Classifier: Programming Language :: Python :: 3
Classifier: Programming Language :: Python :: 3.9
Classifier: Programming Language :: Python :: 3.10
Classifier: Programming Language :: Python :: 3.11
Classifier: Programming Language :: Python :: 3.12
Classifier: Programming Language :: Python :: Implementation :: CPython
Classifier: Programming Language :: Python :: Implementation :: PyPy
Requires-Dist: numpy (==1.26.4)
Requires-Dist: pandas (==2.2.2)
Requires-Dist: pint (==0.23)
Requires-Dist: requests (==2.31.0)
Project-URL: Homepage, https://github.com/bvmcode/ambient_wx
Project-URL: Issues, https://github.com/bvmcode/ambient_wx/issues
Project-URL: Source, https://github.com/bvmcode/ambient_wx
